[
    {
      "name": "Abraham Linkon",
      "email": "abraham@gmail.com",
      "image": "10"
    },
    {
      "name": "Jane Smith",
      "email": "janesmith@gmail.com"
    },
    {
      "name": "Alice Johnson",
      "email": "alicejohnson@gmail.com"
    },
    {
      "name": "Bob Williams",
      "email": "bobwilliams@gmail.com"
    },
    {
      "name": "Charlie Brown",
      "email": "charliebrown@gmail.com",
      "image": "3"
    },
    {
      "name": "Diana Prince",
      "email": "dianaprince@gmail.com"
      "iamge" : "female"
    },
    {
      "name": "Ethan Hunt",
      "email": "ethanhunt@gmail.com"
    },
    {
      "name": "Fiona Gallagher",
      "email": "fionagallagher@gmail.com"
    },
    {
      "name": "George Banks",
      "email": "georgebanks@gmail.com"
    },
    {
      "name": "Hannah Davis",
      "email": "hannahdavis@gmail.com"
    }
  ]
  